flyteplugins/openai/__init__.py
flyteplugins/openai/agents/__init__.py
flyteplugins/openai/agents/_function_tools.py
flyteplugins_openai-2.0.0b53.dist-info/METADATA
flyteplugins_openai-2.0.0b53.dist-info/WHEEL
flyteplugins_openai-2.0.0b53.dist-info/top_level.txt
flyteplugins_openai-2.0.0b53.dist-info/RECORD
