Metadata-Version: 2.4
Name: flyteplugins-openai
Version: 2.0.0b53
Summary: OpenAI plugin for flyte
Author-email: Niels Bantilan <cosmicbboy@users.noreply.github.com>
Requires-Python: >=3.10
Requires-Dist: openai-agents>=0.2.4
Requires-Dist: flyte
